mcp_ocr_mini/__init__.py
mcp_ocr_mini/__main__.py
mcp_ocr_mini/install_tesseract.py
mcp_ocr_mini/server.py
mcp_ocr_mini-0.1.6.dist-info/METADATA
mcp_ocr_mini-0.1.6.dist-info/WHEEL
mcp_ocr_mini-0.1.6.dist-info/entry_points.txt
mcp_ocr_mini-0.1.6.dist-info/licenses/LICENSE
mcp_ocr_mini-0.1.6.dist-info/RECORD
